c_origami/__init__.py
c_origami/main.py
c_origami-0.0.1.dist-info/LICENSE
c_origami-0.0.1.dist-info/METADATA
c_origami-0.0.1.dist-info/WHEEL
c_origami-0.0.1.dist-info/top_level.txt
c_origami-0.0.1.dist-info/RECORD
